{"braindata": {}, "piedata": [{"color": "#0eff7f", "label": "comm:email (10.42%)", "value": 10.42}, {"color": "#17b02c", "label": "comm:im (4.17%)", "value": 4.17}, {"color": "#1f70d5", "label": "maps (2.08%)", "value": 2.08}, {"color": "#f22d2d", "label": "slack:Threads (2.08%)", "value": 2.08}, {"color": "#28d2f7", "label": "slack:haskell (4.17%)", "value": 4.17}], "tagdata": {"comm:email": {"color": "#0eff7f", "minute": [475, 477, 478, 479, 578]}, "comm:im": {"color": "#17b02c", "minute": [482, 483]}, "maps": {"color": "#1f70d5", "minute": [577]}, "slack:Threads": {"color": "#f22d2d", "minute": [521]}, "slack:haskell": {"color": "#28d2f7", "minute": [480, 481]}}}