{"braindata": {}, "piedata": [{"color": "#17b02c", "label": "comm:im (19.93%)", "value": 19.93}, {"color": "#28d2f7", "label": "music:record (4.47%)", "value": 4.47}, {"color": "#2bdd6d", "label": "pp (2.06%)", "value": 2.06}, {"color": "#ff7fe0", "label": "slack:Jonathan_Lorimer (6.19%)", "value": 6.19}, {"color": "#ff9f98", "label": "slack:haskell (2.41%)", "value": 2.41}], "tagdata": {"comm:email": {"color": "#0eff7f", "minute": [466, 1124, 1176, 1376]}, "comm:im": {"color": "#17b02c", "minute": [323, 327, 339, 341, 352, 355, 394, 420, 421, 499, 642, 1113, 1123, 1356, 1357, 1358, 1365, 1373, 1388, 1389, 1390, 1391, 1394, 1395, 1402, 1403, 1406, 1407, 1408, 1409, 1410, 1411, 1413, 1415, 1416, 1417, 1418, 1419, 1420, 1421, 1422, 1423, 1424, 1425, 1426, 1427, 1428, 1429, 1430, 1431, 1432, 1433, 1434, 1435, 1436, 1437, 1438, 1439]}, "music:record": {"color": "#28d2f7", "minute": [1297, 1298, 1299, 1300, 1301, 1302, 1303, 1305, 1306, 1307, 1308, 1309, 1310]}, "pp": {"color": "#2bdd6d", "minute": [1143, 1144, 1145, 1146, 1147, 1148]}, "slack:Jonathan_Lorimer": {"color": "#ff7fe0", "minute": [1195, 1196, 1197, 1198, 1199, 1200, 1201, 1202, 1203, 1204, 1205, 1206, 1207, 1208, 1209, 1210, 1211, 1212]}, "slack:Threads": {"color": "#e0ac7c", "minute": [361]}, "slack:fintan__vikrem": {"color": "#d2fd22", "minute": [362]}, "slack:haskell": {"color": "#ff9f98", "minute": [356, 357, 358, 1327, 1328, 1329, 1330]}, "slack:solomon": {"color": "#2c2377", "minute": [644, 1100]}}}