{"braindata": {}, "piedata": [{"color": "#0726f7", "label": "call (4.37%)", "value": 4.37}, {"color": "#0eff7f", "label": "comm:email (2.13%)", "value": 2.13}, {"color": "#17b02c", "label": "comm:im (1.77%)", "value": 1.77}, {"color": "#17b02c", "label": "slack:chrispenner (2.36%)", "value": 2.36}, {"color": "#2c2377", "label": "slack:general (1.53%)", "value": 1.53}], "tagdata": {"call": {"color": "#0726f7", "minute": [1121, 1122, 1123, 1124, 1125, 1126, 1127, 1128, 1129, 1130, 1131, 1132, 1133, 1134, 1135, 1136, 1137, 1138, 1139, 1140, 1141, 1142, 1143, 1144, 1145, 1146, 1147, 1148, 1149, 1150, 1151, 1152, 1162, 1163, 1164, 1165, 1166]}, "comm:email": {"color": "#0eff7f", "minute": [76, 77, 685, 686, 1110, 1168, 1169, 1186, 1188, 1192, 1195, 1196, 1198, 1231, 1258, 1287, 1311, 1334]}, "comm:im": {"color": "#17b02c", "minute": [75, 78, 79, 80, 537, 684, 925, 926, 927, 928, 943, 953, 1259, 1422, 1423]}, "maps": {"color": "#1f70d5", "minute": [921, 922, 923, 924, 1153, 1154, 1155, 1156, 1157, 1159, 1160]}, "prj:ngs": {"color": "#bcb222", "minute": [1269, 1271, 1275, 1277]}, "prj:sdcp": {"color": "#a77f8e", "minute": [1266, 1267, 1268, 1272, 1276, 1283, 1288, 1289, 1290, 1291, 1324]}, "reddit:haskell": {"color": "#e7cead", "minute": [1346]}, "reddit:ssc": {"color": "#e8af77", "minute": [920, 929, 1187, 1339]}, "slack:Jonathan_Lorimer": {"color": "#ff7f8a", "minute": [1294, 1295, 1299, 1300, 1305, 1307]}, "slack:Matt_Noonan": {"color": "#bcbae5", "minute": [1322]}, "slack:chrispenner": {"color": "#17b02c", "minute": [1293, 1296, 1301, 1302, 1303, 1308, 1312, 1314, 1315, 1316, 1317, 1318, 1319, 1320, 1321, 1323, 1327, 1330, 1331, 1333]}, "slack:general": {"color": "#2c2377", "minute": [538, 539, 540, 541, 542, 543, 544, 545, 546, 547, 548, 549, 550]}, "slack:haskell": {"color": "#56449c", "minute": [918, 919, 1115]}, "web:wikipedia": {"color": "#b418df", "minute": [1278, 1279, 1280, 1286, 1292, 1310]}}}