{"braindata": {}, "piedata": [{"color": "#0726f7", "label": "call (7.71%)", "value": 7.71}, {"color": "#0eff7f", "label": "comm:email (1.68%)", "value": 1.68}, {"color": "#17b02c", "label": "comm:im (14.07%)", "value": 14.07}, {"color": "#2bdd6d", "label": "pp (2.85%)", "value": 2.85}, {"color": "#b4c476", "label": "prj:sdcp (6.53%)", "value": 6.53}, {"color": "#d2fd22", "label": "slack:haskell (2.68%)", "value": 2.68}, {"color": "#ff9f98", "label": "slack:kcsongor (2.01%)", "value": 2.01}, {"color": "#2722e3", "label": "slack:zenzike (2.01%)", "value": 2.01}, {"color": "#56449c", "label": "web:wikipedia (2.01%)", "value": 2.01}], "tagdata": {"call": {"color": "#0726f7", "minute": [61, 105, 146, 147, 148, 149, 150, 151, 152, 153, 154, 155, 156, 157, 158, 159, 160, 161, 162, 163, 164, 165, 166, 167, 168, 169, 170, 171, 172, 173, 174, 175, 176, 177, 178, 179, 180, 181, 182, 183, 184, 185, 186, 187, 188, 189]}, "comm:email": {"color": "#0eff7f", "minute": [23, 195, 203, 217, 225, 973, 974, 1267, 1292, 1392]}, "comm:im": {"color": "#17b02c", "minute": [22, 34, 36, 42, 51, 56, 67, 68, 69, 70, 71, 72, 73, 74, 75, 76, 78, 79, 80, 81, 82, 83, 84, 85, 86, 87, 88, 89, 90, 91, 92, 93, 94, 95, 96, 97, 98, 99, 100, 101, 102, 103, 104, 124, 134, 135, 136, 139, 140, 193, 194, 198, 207, 208, 214, 215, 216, 219, 220, 221, 222, 223, 972, 975, 979, 980, 1137, 1195, 1236, 1237, 1239, 1241, 1248, 1257, 1263, 1321, 1322, 1327, 1329, 1331, 1370, 1371, 1378, 1386]}, "maps": {"color": "#1f70d5", "minute": [218, 236, 249]}, "pp": {"color": "#2bdd6d", "minute": [1145, 1146, 1147, 1148, 1149, 1150, 1151, 1152, 1153, 1154, 1155, 1156, 1157, 1158, 1159, 1160, 1161]}, "prj:eff": {"color": "#9f0637", "minute": [200]}, "prj:sdcp": {"color": "#b4c476", "minute": [1323, 1324, 1325, 1326, 1328, 1330, 1332, 1336, 1337, 1338, 1339, 1340, 1341, 1342, 1343, 1344, 1346, 1348, 1349, 1351, 1352, 1353, 1355, 1356, 1358, 1359, 1360, 1361, 1362, 1363, 1364, 1366, 1367, 1368, 1369, 1373, 1374, 1375, 1379]}, "ref:hackage": {"color": "#bd9b8c", "minute": [26]}, "slack:Jonathan_Lorimer": {"color": "#c5bc56", "minute": [137, 138, 141, 142, 143]}, "slack:Rohan": {"color": "#bcbae5", "minute": [116, 120]}, "slack:TheMatten": {"color": "#cea8ea", "minute": [53, 119, 125, 132]}, "slack:finto": {"color": "#e7cead", "minute": [1365, 1376, 1380, 1381, 1382, 1384]}, "slack:haskell": {"color": "#d2fd22", "minute": [24, 25, 27, 31, 33, 123, 131, 133, 1138, 1143, 1144, 1345, 1347, 1350, 1354, 1357]}, "slack:i-am-tom": {"color": "#7a8fff", "minute": [109, 429]}, "slack:kcsongor": {"color": "#ff9f98", "minute": [107, 108, 110, 111, 113, 114, 115, 117, 118, 122, 190, 202]}, "slack:sicklorkin": {"color": "#7f764b", "minute": [1162, 1259]}, "slack:zenzike": {"color": "#2722e3", "minute": [54, 55, 57, 58, 59, 62, 63, 64, 65, 66, 145, 1320]}, "web:wikipedia": {"color": "#56449c", "minute": [1278, 1387, 1397, 1398, 1399, 1400, 1401, 1402, 1403, 1404, 1405, 1411]}}}