{"braindata": {}, "piedata": [{"color": "#0eff7f", "label": "comm:email (1.63%)", "value": 1.63}, {"color": "#17b02c", "label": "comm:im (9.39%)", "value": 9.39}, {"color": "#2bdd6d", "label": "pp (2.45%)", "value": 2.45}, {"color": "#7f764b", "label": "web:goodreads (4.08%)", "value": 4.08}, {"color": "#8dd728", "label": "web:wikipedia (3.27%)", "value": 3.27}], "tagdata": {"comm:email": {"color": "#0eff7f", "minute": [670, 701, 718, 1411]}, "comm:im": {"color": "#17b02c", "minute": [540, 708, 712, 742, 875, 1011, 1036, 1052, 1053, 1054, 1055, 1059, 1060, 1141, 1145, 1151, 1156, 1161, 1162, 1257, 1258, 1412, 1428]}, "maps": {"color": "#1f70d5", "minute": [539, 702, 873]}, "pp": {"color": "#2bdd6d", "minute": [1134, 1135, 1136, 1137, 1138, 1139]}, "prj:eff": {"color": "#75d0f1", "minute": [1430, 1431, 1432]}, "prj:hskit": {"color": "#92d6a8", "minute": [734]}, "ref:hackage": {"color": "#d827d8", "minute": [1089]}, "slack:Threads": {"color": "#d2fd22", "minute": [1142]}, "slack:chrispenner": {"color": "#ff7f8a", "minute": [855]}, "slack:haskell": {"color": "#2722e3", "minute": [1037, 1414]}, "web:goodreads": {"color": "#7f764b", "minute": [723, 856, 857, 858, 859, 860, 861, 862, 863, 874]}, "web:wikipedia": {"color": "#8dd728", "minute": [1409, 1410, 1415, 1416, 1417, 1418, 1426, 1427]}}}