{"braindata": {}, "piedata": [{"color": "#0eff7f", "label": "comm:email (9.02%)", "value": 9.02}, {"color": "#17b02c", "label": "comm:im (4.51%)", "value": 4.51}, {"color": "#2c2377", "label": "pp (9.77%)", "value": 9.77}, {"color": "#bf3637", "label": "prj:sdcp (1.50%)", "value": 1.5}, {"color": "#aec8ae", "label": "scholarship (1.50%)", "value": 1.5}, {"color": "#bc2071", "label": "tv:youtube (59.40%)", "value": 59.4}], "tagdata": {"comm:email": {"color": "#0eff7f", "minute": [543, 544, 545, 546, 547, 548, 549, 550, 551, 552, 553, 554]}, "comm:im": {"color": "#17b02c", "minute": [60, 61, 62, 63, 524, 525]}, "comm:zulip": {"color": "#1f70d5", "minute": [2]}, "pp": {"color": "#2c2377", "minute": [72, 73, 74, 75, 76, 77, 78, 79, 80, 81, 82, 83, 84]}, "prj:sdcp": {"color": "#bf3637", "minute": [0, 1]}, "reddit:ssc": {"color": "#989fff", "minute": [530]}, "scholarship": {"color": "#aec8ae", "minute": [3, 4]}, "tv:youtube": {"color": "#bc2071", "minute": [87, 88, 89, 90, 91, 92, 93, 94, 95, 96, 97, 98, 99, 100, 101, 102, 103, 104, 105, 106, 107, 108, 109, 110, 111, 112, 113, 114, 115, 116, 117, 118, 119, 120, 121, 122, 123, 124, 125, 126, 127, 128, 154, 155, 156, 157, 158, 159, 160, 161, 162, 163, 164, 165, 166, 167, 168, 169, 170, 171, 172, 173, 174, 175, 176, 177, 178, 522, 531, 532, 533, 534, 535, 536, 537, 538, 539, 540, 541]}}}