{"braindata": {}, "piedata": [{"color": "#0eff7f", "label": "comm:email (6.25%)", "value": 6.25}, {"color": "#17b02c", "label": "comm:im (6.25%)", "value": 6.25}, {"color": "#bcbae5", "label": "prj:sdcp (9.38%)", "value": 9.38}, {"color": "#0eff7f", "label": "slack:haskell (3.12%)", "value": 3.12}], "tagdata": {"comm:email": {"color": "#0eff7f", "minute": [46, 48]}, "comm:im": {"color": "#17b02c", "minute": [43, 49]}, "prj:sdcp": {"color": "#bcbae5", "minute": [50, 51, 52]}, "slack:haskell": {"color": "#0eff7f", "minute": [53]}}}